[
  {
    "title_1": "디엔즈 로우",
    "title_2": "와이드 팬츠",
    "price": 45220,
    "href": "/GirlCrush/1"
  },
  {
    "title_1": "세핀즈 셔링",
    "title_2": "크롭 티셔츠",
    "price": 21000,
    "href": "/GirlCrush/2"
  },
  {
    "title_1": "프런트 하이핏",
    "title_2": "부츠컷팬츠",
    "price": 37050,
    "href": "/GirlCrush/3"
  },
  {
    "title_1": "보넬 나일론",
    "title_2": "루즈핏 점퍼",
    "price": 107000,
    "href": "/GirlCrush/4"
  },
  {
    "title_1": "뷰리팅 레터링",
    "title_2": "티셔츠",
    "price": 24000,
    "href": "/GirlCrush/5"
  },
  {
    "title_1": "스텐비 데님",
    "title_2": "크롭 자켓",
    "price": 66300,
    "href": "/GirlCrush/6"
  },
  {
    "title_1": "디엔즈 로우",
    "title_2": "와이드 팬츠",
    "price": 45220,
    "href": "/GirlCrush/7"
  },
  {
    "title_1": "세핀즈 셔링",
    "title_2": "크롭 티셔츠",
    "price": 21000,
    "href": "/GirlCrush/8"
  },
  {
    "title_1": "프런트 하이핏",
    "title_2": "부츠컷팬츠",
    "price": 37050,
    "href": "/GirlCrush/9"
  },
  {
    "title_1": "보넬 나일론",
    "title_2": "루즈핏 점퍼",
    "price": 107000,
    "href": "/GirlCrush/10"
  },
  {
    "title_1": "뷰리팅 레터링",
    "title_2": "티셔츠",
    "price": 24000,
    "href": "/GirlCrush/11"
  },
  {
    "title_1": "스텐비 데님",
    "title_2": "크롭 자켓",
    "price": 66300,
    "href": "/GirlCrush/12"
  }
]
